options_library/__init__.py
options_library/options.py
options_library-0.1.0.dist-info/licenses/LICENSE
options_library-0.1.0.dist-info/METADATA
options_library-0.1.0.dist-info/WHEEL
options_library-0.1.0.dist-info/top_level.txt
options_library-0.1.0.dist-info/RECORD
