Metadata-Version: 2.4
Name: options_library
Version: 0.1.0
Summary: A Python package for financial options strategies
Author: Arka Roychowdhury
Classifier: Programming Language :: Python :: 3
Classifier: License :: OSI Approved :: MIT License
Classifier: Operating System :: OS Independent
License-File: LICENSE
Dynamic: author
Dynamic: classifier
Dynamic: license-file
Dynamic: summary
